Workbook

Sheet Danh mục
A1: STT | B1: Mã | C1: Giá đóng cửa | D1: % Thay đổi giá | I1: P/E | J1: PB | K1: So với P/E Trung vị 5 năm | L1: So với P/B Trung vị 5 năm | M1: 52w high | N1: 52w low | O1: P/E Tvi 5y | P1: P/B Tvi 5y
D2: 1 tuần | E2: 1 tháng | F2: YTD | G2: 52w High | H2: 52w Low
C3: VNĐ | D3: % | E3: % | F3: % | G3: % | H3: % | I3: Lần | J3: Lần | K3: % | L3: %
A4: 64 | B4: PNJ | C4: =VLOOKUP($B4,'Cập nhật giá'!$B$9:$Q$1603,4,FALSE()) -> 36000 | D4: =VLOOKUP($B4,'Cập nhật giá'!$B$9:$Q$1603,8,FALSE()) -> 0.16129032 | E4: =VLOOKUP($B4,'Cập nhật giá'!$B$9:$Q$1603,9,FALSE()) -> -0.29133858 | F4: =VLOOKUP($B4,'Cập nhật giá'!$B$9:$Q$1603,10,FALSE()) -> -0.43793095 | G4: =C4/M4-1 -> -0.57482441 | H4: =C4/N4-1 -> 0.17073171 | I4: =VLOOKUP($B4,'Cập nhật giá'!$B$9:$Q$1603,11,FALSE()) -> 6.35 | J4: =VLOOKUP($B4,'Cập nhật giá'!$B$9:$Q$1603,12,FALSE()) -> 1.33 | K4: =I4/O4-1 -> -0.57723036 | L4: =J4/P4-1 -> -0.55960265 | M4: =VLOOKUP($B4,'Cập nhật giá'!$B$9:$Q$1603,13,FALSE()) -> 84670.9 | N4: =VLOOKUP($B4,'Cập nhật giá'!$B$9:$Q$1603,14,FALSE()) -> 30750 | O4: =VLOOKUP($B4,'Cập nhật giá'!$B$9:$Q$1603,15,FALSE()) -> 15.02 | P4: =VLOOKUP($B4,'Cập nhật giá'!$B$9:$Q$1603,16,FALSE()) -> 3.02
A5: 39 | B5: DGC | C5: =VLOOKUP($B5,'Cập nhật giá'!$B$9:$Q$1603,4,FALSE()) -> 44200 | D5: =VLOOKUP($B5,'Cập nhật giá'!$B$9:$Q$1603,8,FALSE()) -> 0.13043478 | E5: =VLOOKUP($B5,'Cập nhật giá'!$B$9:$Q$1603,9,FALSE()) -> -0.035986914 | F5: =VLOOKUP($B5,'Cập nhật giá'!$B$9:$Q$1603,10,FALSE()) -> -0.35474453 | G5: =C5/M5-1 -> -0.57244697 | H5: =C5/N5-1 -> 0.22777778 | I5: =VLOOKUP($B5,'Cập nhật giá'!$B$9:$Q$1603,11,FALSE()) -> 7.86 | J5: =VLOOKUP($B5,'Cập nhật giá'!$B$9:$Q$1603,12,FALSE()) -> 1.06 | K5: =I5/O5-1 -> -0.29348315 | L5: =J5/P5-1 -> -0.64309764 | M5: =VLOOKUP($B5,'Cập nhật giá'!$B$9:$Q$1603,13,FALSE()) -> 103378.99 | N5: =VLOOKUP($B5,'Cập nhật giá'!$B$9:$Q$1603,14,FALSE()) -> 36000 | O5: =VLOOKUP($B5,'Cập nhật giá'!$B$9:$Q$1603,15,FALSE()) -> 11.125 | P5: =VLOOKUP($B5,'Cập nhật giá'!$B$9:$Q$1603,16,FALSE()) -> 2.97
A6: 33 | B6: PLX | C6: =VLOOKUP($B6,'Cập nhật giá'!$B$9:$Q$1603,4,FALSE()) -> 35950 | D6: =VLOOKUP($B6,'Cập nhật giá'!$B$9:$Q$1603,8,FALSE()) -> 0.11827178 | E6: =VLOOKUP($B6,'Cập nhật giá'!$B$9:$Q$1603,9,FALSE()) -> 0.067004309 | F6: =VLOOKUP($B6,'Cập nhật giá'!$B$9:$Q$1603,10,FALSE()) -> 0.054913609 | G6: =C6/M6-1 -> -0.46419496 | H6: =C6/N6-1 -> 0.14053447 | I6: =VLOOKUP($B6,'Cập nhật giá'!$B$9:$Q$1603,11,FALSE()) -> 14.18 | J6: =VLOOKUP($B6,'Cập nhật giá'!$B$9:$Q$1603,12,FALSE()) -> 1.77 | K6: =I6/O6-1 -> -0.32217973 | L6: =J6/P6-1 -> -0.092307692 | M6: =VLOOKUP($B6,'Cập nhật giá'!$B$9:$Q$1603,13,FALSE()) -> 67095.3 | N6: =VLOOKUP($B6,'Cập nhật giá'!$B$9:$Q$1603,14,FALSE()) -> 31520.31 | O6: =VLOOKUP($B6,'Cập nhật giá'!$B$9:$Q$1603,15,FALSE()) -> 20.92 | P6: =VLOOKUP($B6,'Cập nhật giá'!$B$9:$Q$1603,16,FALSE()) -> 1.95
A7: 57 | B7: GEX | C7: =VLOOKUP($B7,'Cập nhật giá'!$B$9:$Q$1603,4,FALSE()) -> 24550 | D7: =VLOOKUP($B7,'Cập nhật giá'!$B$9:$Q$1603,8,FALSE()) -> 0.091111111 | E7: =VLOOKUP($B7,'Cập nhật giá'!$B$9:$Q$1603,9,FALSE()) -> -0.16354344 | F7: =VLOOKUP($B7,'Cập nhật giá'!$B$9:$Q$1603,10,FALSE()) -> -0.18359664 | G7: =C7/M7-1 -> -0.4557311 | H7: =C7/N7-1 -> 0.20935961 | I7: =VLOOKUP($B7,'Cập nhật giá'!$B$9:$Q$1603,11,FALSE()) -> 23.42 | J7: =VLOOKUP($B7,'Cập nhật giá'!$B$9:$Q$1603,12,FALSE()) -> 1.62 | K7: =I7/O7-1 -> -0.02599293 | L7: =J7/P7-1 -> 0.018867925 | M7: =VLOOKUP($B7,'Cập nhật giá'!$B$9:$Q$1603,13,FALSE()) -> 45106.38 | N7: =VLOOKUP($B7,'Cập nhật giá'!$B$9:$Q$1603,14,FALSE()) -> 20300 | O7: =VLOOKUP($B7,'Cập nhật giá'!$B$9:$Q$1603,15,FALSE()) -> 24.045 | P7: =VLOOKUP($B7,'Cập nhật giá'!$B$9:$Q$1603,16,FALSE()) -> 1.59
A8: 10 | B8: GAS | C8: =VLOOKUP($B8,'Cập nhật giá'!$B$9:$Q$1603,4,FALSE()) -> 74600 | D8: =VLOOKUP($B8,'Cập nhật giá'!$B$9:$Q$1603,8,FALSE()) -> 0.087463557 | E8: =VLOOKUP($B8,'Cập nhật giá'!$B$9:$Q$1603,9,FALSE()) -> 0.010840108 | F8: =VLOOKUP($B8,'Cập nhật giá'!$B$9:$Q$1603,10,FALSE()) -> 0.03038674 | G8: =C8/M8-1 -> -0.42035742 | H8: =C8/N8-1 -> 0.33214286 | I8: =VLOOKUP($B8,'Cập nhật giá'!$B$9:$Q$1603,11,FALSE()) -> 14.17 | J8: =VLOOKUP($B8,'Cập nhật giá'!$B$9:$Q$1603,12,FALSE()) -> 2.62 | K8: =I8/O8-1 -> -0.088452879 | L8: =J8/P8-1 -> -0.093425606 | M8: =VLOOKUP($B8,'Cập nhật giá'!$B$9:$Q$1603,13,FALSE()) -> 128700 | N8: =VLOOKUP($B8,'Cập nhật giá'!$B$9:$Q$1603,14,FALSE()) -> 56000 | O8: =VLOOKUP($B8,'Cập nhật giá'!$B$9:$Q$1603,15,FALSE()) -> 15.545 | P8: =VLOOKUP($B8,'Cập nhật giá'!$B$9:$Q$1603,16,FALSE()) -> 2.89
A9: 38 | B9: GVR | C9: =VLOOKUP($B9,'Cập nhật giá'!$B$9:$Q$1603,4,FALSE()) -> 29750 | D9: =VLOOKUP($B9,'Cập nhật giá'!$B$9:$Q$1603,8,FALSE()) -> 0.081818182 | E9: =VLOOKUP($B9,'Cập nhật giá'!$B$9:$Q$1603,9,FALSE()) -> -0.054054054 | F9: =VLOOKUP($B9,'Cập nhật giá'!$B$9:$Q$1603,10,FALSE()) -> 0.13549618 | G9: =C9/M9-1 -> -0.34972678 | H9: =C9/N9-1 -> 0.19506804 | I9: =VLOOKUP($B9,'Cập nhật giá'!$B$9:$Q$1603,11,FALSE()) -> 16.69 | J9: =VLOOKUP($B9,'Cập nhật giá'!$B$9:$Q$1603,12,FALSE()) -> 1.96 | K9: =I9/O9-1 -> -0.35955487 | L9: =J9/P9-1 -> -0.096774194 | M9: =VLOOKUP($B9,'Cập nhật giá'!$B$9:$Q$1603,13,FALSE()) -> 45750 | N9: =VLOOKUP($B9,'Cập nhật giá'!$B$9:$Q$1603,14,FALSE()) -> 24893.98 | O9: =VLOOKUP($B9,'Cập nhật giá'!$B$9:$Q$1603,15,FALSE()) -> 26.06 | P9: =VLOOKUP($B9,'Cập nhật giá'!$B$9:$Q$1603,16,FALSE()) -> 2.17
A10: 68 | B10: BCM | C10: =VLOOKUP($B10,'Cập nhật giá'!$B$9:$Q$1603,4,FALSE()) -> 38600 | D10: =VLOOKUP($B10,'Cập nhật giá'!$B$9:$Q$1603,8,FALSE()) -> 0.081232493 | E10: =VLOOKUP($B10,'Cập nhật giá'!$B$9:$Q$1603,9,FALSE()) -> -0.23865878 | F10: =VLOOKUP($B10,'Cập nhật giá'!$B$9:$Q$1603,10,FALSE()) -> -0.36460278 | G10: =C10/M10-1 -> -0.50915565 | H10: =C10/N10-1 -> 0.10285714 | I10: =VLOOKUP($B10,'Cập nhật giá'!$B$9:$Q$1603,11,FALSE()) -> 18.68 | J10: =VLOOKUP($B10,'Cập nhật giá'!$B$9:$Q$1603,12,FALSE()) -> 1.83 | K10: =I10/O10-1 -> -0.35296155 | L10: =J10/P10-1 -> -0.51004016 | M10: =VLOOKUP($B10,'Cập nhật giá'!$B$9:$Q$1603,13,FALSE()) -> 78640 | N10: =VLOOKUP($B10,'Cập nhật giá'!$B$9:$Q$1603,14,FALSE()) -> 35000 | O10: =VLOOKUP($B10,'Cập nhật giá'!$B$9:$Q$1603,15,FALSE()) -> 28.87 | P10: =VLOOKUP($B10,'Cập nhật giá'!$B$9:$Q$1603,16,FALSE()) -> 3.735
A11: 36 | B11: DGW | C11: =VLOOKUP($B11,'Cập nhật giá'!$B$9:$Q$1603,4,FALSE()) -> 39400 | D11: =VLOOKUP($B11,'Cập nhật giá'!$B$9:$Q$1603,8,FALSE()) -> 0.076502732 | E11: =VLOOKUP($B11,'Cập nhật giá'!$B$9:$Q$1603,9,FALSE()) -> 0 | F11: =VLOOKUP($B11,'Cập nhật giá'!$B$9:$Q$1603,10,FALSE()) -> 0.034780713 | G11: =C11/M11-1 -> -0.27934915 | H11: =C11/N11-1 -> 0.18853695 | I11: =VLOOKUP($B11,'Cập nhật giá'!$B$9:$Q$1603,11,FALSE()) -> 10.41 | J11: =VLOOKUP($B11,'Cập nhật giá'!$B$9:$Q$1603,12,FALSE()) -> 2.34 | K11: =I11/O11-1 -> -0.43607801 | L11: =J11/P11-1 -> -0.2972973 | M11: =VLOOKUP($B11,'Cập nhật giá'!$B$9:$Q$1603,13,FALSE()) -> 54672.8 | N11: =VLOOKUP($B11,'Cập nhật giá'!$B$9:$Q$1603,14,FALSE()) -> 33150 | O11: =VLOOKUP($B11,'Cập nhật giá'!$B$9:$Q$1603,15,FALSE()) -> 18.46 | P11: =VLOOKUP($B11,'Cập nhật giá'!$B$9:$Q$1603,16,FALSE()) -> 3.33
A12: 8 | B12: NVL | C12: =VLOOKUP($B12,'Cập nhật giá'!$B$9:$Q$1603,4,FALSE()) -> 13900 | D12: =VLOOKUP($B12,'Cập nhật giá'!$B$9:$Q$1603,8,FALSE()) -> 0.069230769 | E12: =VLOOKUP($B12,'Cập nhật giá'!$B$9:$Q$1603,9,FALSE()) -> 0.10756972 | F12: =VLOOKUP($B12,'Cập nhật giá'!$B$9:$Q$1603,10,FALSE()) -> 0.11932757 | G12: =C12/M12-1 -> -0.27107205 | H12: =C12/N12-1 -> 0.42314505 | I12: =VLOOKUP($B12,'Cập nhật giá'!$B$9:$Q$1603,11,FALSE()) -> 8.18 | J12: =VLOOKUP($B12,'Cập nhật giá'!$B$9:$Q$1603,12,FALSE()) -> 0.69 | K12: =I12/O12-1 -> -0.48063492 | L12: =J12/P12-1 -> -0.12658228 | M12: =VLOOKUP($B12,'Cập nhật giá'!$B$9:$Q$1603,13,FALSE()) -> 19069.1 | N12: =VLOOKUP($B12,'Cập nhật giá'!$B$9:$Q$1603,14,FALSE()) -> 9767.1 | O12: =VLOOKUP($B12,'Cập nhật giá'!$B$9:$Q$1603,15,FALSE()) -> 15.75 | P12: =VLOOKUP($B12,'Cập nhật giá'!$B$9:$Q$1603,16,FALSE()) -> 0.79
A13: 32 | B13: DIG | C13: =VLOOKUP($B13,'Cập nhật giá'!$B$9:$Q$1603,4,FALSE()) -> 10700 | D13: =VLOOKUP($B13,'Cập nhật giá'!$B$9:$Q$1603,8,FALSE()) -> 0.064676617 | E13: =VLOOKUP($B13,'Cập nhật giá'!$B$9:$Q$1603,9,FALSE()) -> -0.10084034 | F13: =VLOOKUP($B13,'Cập nhật giá'!$B$9:$Q$1603,10,FALSE()) -> -0.36119403 | G13: =C13/M13-1 -> -0.56504065 | H13: =C13/N13-1 -> 0.10423117 | I13: =VLOOKUP($B13,'Cập nhật giá'!$B$9:$Q$1603,11,FALSE()) -> 10.18 | J13: =VLOOKUP($B13,'Cập nhật giá'!$B$9:$Q$1603,12,FALSE()) -> 0.84 | K13: =I13/O13-1 -> -0.80600286 | L13: =J13/P13-1 -> -0.56020942 | M13: =VLOOKUP($B13,'Cập nhật giá'!$B$9:$Q$1603,13,FALSE()) -> 24600 | N13: =VLOOKUP($B13,'Cập nhật giá'!$B$9:$Q$1603,14,FALSE()) -> 9690 | O13: =VLOOKUP($B13,'Cập nhật giá'!$B$9:$Q$1603,15,FALSE()) -> 52.475 | P13: =VLOOKUP($B13,'Cập nhật giá'!$B$9:$Q$1603,16,FALSE()) -> 1.91
A14: 30 | B14: FRT | C14: =VLOOKUP($B14,'Cập nhật giá'!$B$9:$Q$1603,4,FALSE()) -> 132000 | D14: =VLOOKUP($B14,'Cập nhật giá'!$B$9:$Q$1603,8,FALSE()) -> 0.061093248 | E14: =VLOOKUP($B14,'Cập nhật giá'!$B$9:$Q$1603,9,FALSE()) -> 0.12820513 | F14: =VLOOKUP($B14,'Cập nhật giá'!$B$9:$Q$1603,10,FALSE()) -> -0.07292824 | G14: =C14/M14-1 -> -0.2102722 | H14: =C14/N14-1 -> 0.25714286 | I14: =VLOOKUP($B14,'Cập nhật giá'!$B$9:$Q$1603,11,FALSE()) -> 20.76 | J14: =VLOOKUP($B14,'Cập nhật giá'!$B$9:$Q$1603,12,FALSE()) -> 4.92 | K14: =I14/O14-1 -> -0.12901196 | L14: =J14/P14-1 -> -0.28643945 | M14: =VLOOKUP($B14,'Cập nhật giá'!$B$9:$Q$1603,13,FALSE()) -> 167146.2 | N14: =VLOOKUP($B14,'Cập nhật giá'!$B$9:$Q$1603,14,FALSE()) -> 105000 | O14: =VLOOKUP($B14,'Cập nhật giá'!$B$9:$Q$1603,15,FALSE()) -> 23.835 | P14: =VLOOKUP($B14,'Cập nhật giá'!$B$9:$Q$1603,16,FALSE()) -> 6.895
A15: 54 | B15: CTG | C15: =VLOOKUP($B15,'Cập nhật giá'!$B$9:$Q$1603,4,FALSE()) -> 32500 | D15: =VLOOKUP($B15,'Cập nhật giá'!$B$9:$Q$1603,8,FALSE()) -> 0.055194805 | E15: =VLOOKUP($B15,'Cập nhật giá'!$B$9:$Q$1603,9,FALSE()) -> -0.036448914 | F15: =VLOOKUP($B15,'Cập nhật giá'!$B$9:$Q$1603,10,FALSE()) -> -0.076877631 | G15: =C15/M15-1 -> -0.20478013 | H15: =C15/N15-1 -> 0.13043478 | I15: =VLOOKUP($B15,'Cập nhật giá'!$B$9:$Q$1603,11,FALSE()) -> 6.28 | J15: =VLOOKUP($B15,'Cập nhật giá'!$B$9:$Q$1603,12,FALSE()) -> 1.27 | K15: =I15/O15-1 -> -0.27981651 | L15: =J15/P15-1 -> -0.086330935 | M15: =VLOOKUP($B15,'Cập nhật giá'!$B$9:$Q$1603,13,FALSE()) -> 40869.2 | N15: =VLOOKUP($B15,'Cập nhật giá'!$B$9:$Q$1603,14,FALSE()) -> 28750 | O15: =VLOOKUP($B15,'Cập nhật giá'!$B$9:$Q$1603,15,FALSE()) -> 8.72 | P15: =VLOOKUP($B15,'Cập nhật giá'!$B$9:$Q$1603,16,FALSE()) -> 1.39
... A73: 7 | B73: PC1 | C73: =VLOOKUP($B73,'Cập nhật giá'!$B$9:$Q$1603,4,FALSE()) -> 20650 | D73: =VLOOKUP($B73,'Cập nhật giá'!$B$9:$Q$1603,8,FALSE()) -> -0.035046729 | E73: =VLOOKUP($B73,'Cập nhật giá'!$B$9:$Q$1603,9,FALSE()) -> -0.043981481 | F73: =VLOOKUP($B73,'Cập nhật giá'!$B$9:$Q$1603,10,FALSE()) -> -0.084257206 | G73: =C73/M73-1 -> -0.34130781 | H73: =C73/N73-1 -> 0.16997167 | I73: =VLOOKUP($B73,'Cập nhật giá'!$B$9:$Q$1603,11,FALSE()) -> 7.22 | J73: =VLOOKUP($B73,'Cập nhật giá'!$B$9:$Q$1603,12,FALSE()) -> 1.27 | K73: =I73/O73-1 -> -0.58481886 | L73: =J73/P73-1 -> -0.19620253 | M73: =VLOOKUP($B73,'Cập nhật giá'!$B$9:$Q$1603,13,FALSE()) -> 31350 | N73: =VLOOKUP($B73,'Cập nhật giá'!$B$9:$Q$1603,14,FALSE()) -> 17650 | O73: =VLOOKUP($B73,'Cập nhật giá'!$B$9:$Q$1603,15,FALSE()) -> 17.39 | P73: =VLOOKUP($B73,'Cập nhật giá'!$B$9:$Q$1603,16,FALSE()) -> 1.58

Sheet Cập nhật giá
A5: Tính năng | B5: DE - Doanh nghiệp
A6: Ngày trích xuất
A8: STT | B8: Mã | C8: Tên công ty | D8: Sàn | E8: Giá đóng cửa điều chỉnh (D) Ngày: Hôm nay Đơn vị: VND | F8: Giá đóng cửa điều chỉnh (D) Ngày: 1 tuần trước Đơn vị: VND | G8: Giá đóng cửa điều chỉnh (D) Ngày: 1 tháng trước Đơn vị: VND | H8: Giá đóng cửa điều chỉnh (D) Ngày: 31/12/2025 Đơn vị: VND | I8: % tuần | J8: % tháng | K8: % ytd | L8: P/E pha loãng Chỉ số TTM Đơn vị: Lần | M8: P/B Chỉ số TTM Đơn vị: Lần | N8: Giá cao nhất 52 tuần Đơn vị: VND | O8: Giá thấp nhất 52 tuần Đơn vị: VND | P8: P/E Trung vị 5 năm Đơn vị: Lần | Q8: P/B Trung vị 5 năm Đơn vị: Lần
A9: 1 | B9: AG1 | C9: 28.1 JSC | D9: UPCoM | E9: 11400 | F9: 10945 | G9: 10722 | H9: 10845.8 | I9: =$E9/F9-1 -> 0.041571494 | J9: =$E9/G9-1 -> 0.063234471 | K9: =$E9/H9-1 -> 0.051098121 | L9: 4.97 | M9: 0.95 | N9: 12090.4 | O9: 9864.34
A10: 2 | B10: MT9 | C10: 319 Miền Trung | D10: UPCoM | I10: =$E10/F10-1 -> #DIV/0! | J10: =$E10/G10-1 -> #DIV/0! | K10: =$E10/H10-1 -> #DIV/0!
A11: 3 | B11: NBB | C11: 577 CORP | D11: HOSE | E11: 17300 | F11: 17300 | G11: 17450 | H11: 19500 | I11: =$E11/F11-1 -> 0 | J11: =$E11/G11-1 -> -0.0085959885 | K11: =$E11/H11-1 -> -0.11282051 | L11: 182.09 | M11: 0.96 | N11: 26800 | O11: 16100
A12: 4 | B12: AAV | C12: AAV Group | D12: UPCoM | E12: 6367 | F12: 6452 | G12: 6828 | H12: 6300 | I12: =$E12/F12-1 -> -0.01317421 | J12: =$E12/G12-1 -> -0.06751611 | K12: =$E12/H12-1 -> 0.010634921 | L12: -20.33 | M12: 0.62 | N12: 9000 | O12: 5400
A13: 5 | B13: ACB | C13: ACB | D13: HOSE | E13: 22400 | F13: 21900 | G13: 22600 | H13: 20678.4 | I13: =$E13/F13-1 -> 0.02283105 | J13: =$E13/G13-1 -> -0.0088495575 | K13: =$E13/H13-1 -> 0.083255958 | L13: 8.29 | M13: 1.31 | N13: 25374.12 | O13: 18696.72 | P13: 6.93 | Q13: 1.42
A14: 6 | B14: AGR | C14: Agriseco | D14: HOSE | E14: 13050 | F14: 12900 | G14: 16000 | H14: 16100 | I14: =$E14/F14-1 -> 0.011627907 | J14: =$E14/G14-1 -> -0.184375 | K14: =$E14/H14-1 -> -0.18944099 | L14: 17.38 | M14: 1.13 | N14: 20550 | O14: 12250
A15: 7 | B15: AAA | C15: An Phát Bioplastics | D15: HOSE | E15: 7150 | F15: 7110 | G15: 7186.5 | H15: 7550.62 | I15: =$E15/F15-1 -> 0.005625879 | J15: =$E15/G15-1 -> -0.0050789675 | K15: =$E15/H15-1 -> -0.053057895 | L15: 5.15 | M15: 0.5 | N15: 8480.07 | O15: 6410.36
A16: 8 | B16: HII | C16: An Tiến Industries | D16: HOSE | E16: 8600 | F16: 7090 | G16: 5900 | H16: 5852.34 | I16: =$E16/F16-1 -> 0.21297602 | J16: =$E16/G16-1 -> 0.45762712 | K16: =$E16/H16-1 -> 0.46949767 | L16: 2.7 | M16: 0.57 | N16: 8850 | O16: 4329.78
A17: 9 | B17: VNS | C17: Ánh Dương Việt Nam | D17: HOSE | E17: 7390 | F17: 7500 | G17: 7830 | H17: 9100 | I17: =$E17/F17-1 -> -0.014666667 | J17: =$E17/G17-1 -> -0.056194125 | K17: =$E17/H17-1 -> -0.18791209 | L17: 446.42 | M17: 0.45 | N17: 9830 | O17: 7390
A18: 10 | B18: AMP | C18: Armephaco | D18: UPCoM | E18: 15500 | F18: 16000 | G18: 14500 | H18: 14700 | I18: =$E18/F18-1 -> -0.03125 | J18: =$E18/G18-1 -> 0.068965517 | K18: =$E18/H18-1 -> 0.054421769 | L18: 26.81 | M18: 0.96 | N18: 16500 | O18: 11000
A19: 11 | B19: ATG | C19: ATG Planet | D19: UPCoM | E19: 8100 | F19: 8133 | G19: 8600 | H19: 9500 | I19: =$E19/F19-1 -> -0.0040575433 | J19: =$E19/G19-1 -> -0.058139535 | K19: =$E19/H19-1 -> -0.14736842 | L19: 3.48 | M19: 13.93 | N19: 11500 | O19: 5500
A20: 12 | B20: TSB | C20: Ắc quy Tia Sáng | D20: HNX | E20: 21200 | F20: 20100 | G20: 21300 | H20: 27800 | I20: =$E20/F20-1 -> 0.054726368 | J20: =$E20/G20-1 -> -0.0046948357 | K20: =$E20/H20-1 -> -0.23741007 | L20: -103.41 | M20: 1.93 | N20: 41000 | O20: 18700
A21: 13 | B21: BCG | C21: Bamboo Capital | D21: UPCoM | E21: 2500 | F21: 2500 | G21: 2530 | H21: 2530 | I21: =$E21/F21-1 -> 0 | J21: =$E21/G21-1 -> -0.011857708 | K21: =$E21/H21-1 -> -0.011857708 | L21: 4.7 | M21: 0.22 | N21: 3890 | O21: 2500
A22: 14 | B22: DBM | C22: BAMEPHARM | D22: UPCoM | E22: 31177 | F22: 29000 | G22: 25706.88 | H22: 23921.68 | I22: =$E22/F22-1 -> 0.075068966 | J22: =$E22/G22-1 -> 0.21278817 | K22: =$E22/H22-1 -> 0.30329475 | L22: 13.03 | M22: 0.87 | N22: 31177 | O22: 18744.6
A23: 15 | B23: ECI | C23: Bản đồ và tranh ảnh GD | D23: HNX | E23: 9200 | F23: 9200 | G23: 9200 | H23: 9500 | I23: =$E23/F23-1 -> 0 | J23: =$E23/G23-1 -> 0 | K23: =$E23/H23-1 -> -0.031578947 | L23: -33.98 | M23: 0.53 | N23: 16200 | O23: 7200
A24: 16 | B24: FRT | C24: Bán lẻ FPT | D24: HOSE | E24: 132000 | F24: 124400 | G24: 117000 | H24: 142383.8 | I24: =$E24/F24-1 -> 0.061093248 | J24: =$E24/G24-1 -> 0.12820513 | K24: =$E24/H24-1 -> -0.07292824 | L24: 20.76 | M24: 4.92 | N24: 167146.2 | O24: 105000 | P24: 23.835 | Q24: 6.895
A25: 17 | B25: HCO | C25: Bánh kẹo Hải Châu | D25: UPCoM | I25: =$E25/F25-1 -> #DIV/0! | J25: =$E25/G25-1 -> #DIV/0! | K25: =$E25/H25-1 -> #DIV/0!
A26: 18 | B26: HHC | C26: Bánh kẹo Hải Hà | D26: HNX | E26: 74700 | F26: 74200 | G26: 74500 | H26: 149700 | I26: =$E26/F26-1 -> 0.0067385445 | J26: =$E26/G26-1 -> 0.0026845638 | K26: =$E26/H26-1 -> -0.501002 | L26: 22.5 | M26: 1.8 | N26: 167000 | O26: 67700
A27: 19 | B27: HNF | C27: Bánh kẹo Hữu Nghị | D27: UPCoM | E27: 23400 | F27: 23400 | G27: 24000 | H27: 32017.52 | I27: =$E27/F27-1 -> 0 | J27: =$E27/G27-1 -> -0.025 | K27: =$E27/H27-1 -> -0.26915014 | L27: 6.93 | M27: 1.05 | N27: 34272.28 | O27: 20500
A28: 20 | B28: SGC | C28: Bánh phồng tôm Sa Giang | D28: HNX | E28: 104100 | F28: 106000 | G28: 106100 | H28: 82000 | I28: =$E28/F28-1 -> -0.017924528 | J28: =$E28/G28-1 -> -0.018850141 | K28: =$E28/H28-1 -> 0.2695122 | L28: 5.66 | M28: 1.42 | N28: 113800 | O28: 75400
A29: 21 | B29: BAL | C29: Bao bì Balpac | D29: UPCoM | E29: 7500 | F29: 7500 | G29: 7100 | H29: 9500 | I29: =$E29/F29-1 -> 0 | J29: =$E29/G29-1 -> 0.056338028 | K29: =$E29/H29-1 -> -0.21052632 | L29: 9.67 | M29: 0.49 | N29: 10426.9 | O29: 6200
A30: 22 | B30: BPC | C30: Bao bì Bỉm Sơn | D30: HNX | E30: 12500 | F30: 12500 | G30: 12500 | H30: 12300 | I30: =$E30/F30-1 -> 0 | J30: =$E30/G30-1 -> 0 | K30: =$E30/H30-1 -> 0.016260163 | L30: 22.69 | M30: 0.5 | N30: 14583.92 | O30: 10149.62
A31: 23 | B31: PBP | C31: Bao bì Dầu khí VN | D31: HNX | E31: 11400 | F31: 11700 | G31: 11200 | H31: 12600 | I31: =$E31/F31-1 -> -0.025641026 | J31: =$E31/G31-1 -> 0.017857143 | K31: =$E31/H31-1 -> -0.095238095 | L31: 6.86 | M31: 0.75 | N31: 13500 | O31: 11100
A32: 24 | B32: PMP | C32: Bao bì Đạm Phú Mỹ | D32: HNX | E32: 12000 | F32: 12000 | G32: 12000 | H32: 12500 | I32: =$E32/F32-1 -> 0 | J32: =$E32/G32-1 -> 0 | K32: =$E32/H32-1 -> -0.04 | L32: 5.53 | M32: 0.66 | N32: 14932.8 | O32: 11500
A33: 25 | B33: BBH | C33: Bao bì Hoàng Thạch | D33: UPCoM | E33: 9000 | F33: 8447 | G33: 7719 | H33: 13412.22 | I33: =$E33/F33-1 -> 0.06546703 | J33: =$E33/G33-1 -> 0.16595414 | K33: =$E33/H33-1 -> -0.32897015 | L33: 25.38 | M33: 0.25 | N33: 16522.3 | O33: 6839
A34: 26 | B34: HPB | C34: Bao bì PP | D34: UPCoM | E34: 18500 | F34: 18100 | G34: 20000 | H34: 14733.56 | I34: =$E34/F34-1 -> 0.022099448 | J34: =$E34/G34-1 -> -0.075 | K34: =$E34/H34-1 -> 0.25563679 | L34: 8.21 | M34: 0.51 | N34: 37744.56 | O34: 11833.87
A35: 27 | B35: HBD | C35: Bao bì PP Bình Dương | D35: UPCoM | E35: 26000 | F35: 26400 | G35: 25500 | H35: 17751.7 | I35: =$E35/F35-1 -> -0.015151515 | J35: =$E35/G35-1 -> 0.019607843 | K35: =$E35/H35-1 -> 0.46464846 | L35: 12.45 | M35: 1.35 | N35: 26400 | O35: 15415.95
A36: 28 | B36: TKA | C36: Bao bì Tân Khánh An | D36: UPCoM | E36: 3000 | F36: 3000 | G36: 3000 | H36: 3000 | I36: =$E36/F36-1 -> 0 | J36: =$E36/G36-1 -> 0 | K36: =$E36/H36-1 -> 0 | L36: 1.09 | M36: 0.2 | N36: 3000 | O36: 2965.46
A37: 29 | B37: BTG | C37: Bao bì Tiền Giang | D37: UPCoM | E37: 8100 | F37: 8100 | G37: 8100 | H37: 7600 | I37: =$E37/F37-1 -> 0 | J37: =$E37/G37-1 -> 0 | K37: =$E37/H37-1 -> 0.065789474 | L37: -5.86 | M37: 0.62 | N37: 10300 | O37: 7600
... A62: 54 | B62: LEC | C62: BĐS Điện lực Miền Trung | D62: UPCoM | E62: 4500 | F62: 4500 | G62: 5000 | H62: 3300 | I62: =$E62/F62-1 -> 0 | J62: =$E62/G62-1 -> -0.1 | K62: =$E62/H62-1 -> 0.36363636 | L62: -5.62 | M62: 0.52 | N62: 5806 | O62: 3100
A63: 55 | B63: NLG | C63: BĐS Nam Long | D63: HOSE | E63: 22200 | F63: 22200 | G63: 25650 | H63: 29874.5 | I63: =$E63/F63-1 -> 0 | J63: =$E63/G63-1 -> -0.13450292 | K63: =$E63/H63-1 -> -0.25689133 | L63: 15.77 | M63: 0.86 | N63: 42252.15 | O63: 20000 | P63: 21.32 | Q63: 1.58
A64: 56 | B64: PDR | C64: BĐS Phát Đạt | D64: HOSE | E64: 11900 | F64: 11450 | G64: 14300 | H64: 18800 | I64: =$E64/F64-1 -> 0.03930131 | J64: =$E64/G64-1 -> -0.16783217 | K64: =$E64/H64-1 -> -0.36702128 | L64: 19.22 | M64: 0.94 | N64: 26300 | O64: 11150 | P64: 27.94 | Q64: 1.79
A65: 57 | B65: LSG | C65: BĐS Sài Gòn Vina | D65: UPCoM | E65: 35075 | F65: 32497 | G65: 33565 | H65: 32297 | I65: =$E65/F65-1 -> 0.0793304 | J65: =$E65/G65-1 -> 0.044987338 | K65: =$E65/H65-1 -> 0.086014181 | L65: 46.35 | M65: 2.86 | N65: 38833 | O65: 19870
A66: 58 | B66: PPI | C66: BĐS Thái Bình Dương | D66: UPCoM | E66: 400 | F66: 400 | G66: 400 | H66: 400 | I66: =$E66/F66-1 -> 0 | J66: =$E66/G66-1 -> 0 | K66: =$E66/H66-1 -> 0 | L66: -5.72 | M66: -0.13 | N66: 400 | O66: 400
A67: 59 | B67: BCM | C67: Becamex Group | D67: HOSE | E67: 38600 | F67: 35700 | G67: 50700 | H67: 60749.4 | I67: =$E67/F67-1 -> 0.081232493 | J67: =$E67/G67-1 -> -0.23865878 | K67: =$E67/H67-1 -> -0.36460278 | L67: 18.68 | M67: 1.83 | N67: 78640 | O67: 35000 | P67: 28.87 | Q67: 3.735
A68: 60 | B68: IJC | C68: Becamex IJC | D68: HOSE | E68: 7420 | F68: 7180 | G68: 8630 | H68: 10186.7 | I68: =$E68/F68-1 -> 0.033426184 | J68: =$E68/G68-1 -> -0.14020857 | K68: =$E68/H68-1 -> -0.27159924 | L68: 6.22 | M68: 0.59 | N68: 13455.92 | O68: 6690 | P68: 9.225 | Q68: 1.03
A69: 61 | B69: TDC | C69: Becamex TDC | D69: HOSE | E69: 7250 | F69: 7070 | G69: 9170 | H69: 10887.86 | I69: =$E69/F69-1 -> 0.025459689 | J69: =$E69/G69-1 -> -0.20937841 | K69: =$E69/H69-1 -> -0.33412075 | L69: 4.21 | M69: 0.53 | N69: 13379.15 | O69: 6870
A70: 62 | B70: UDJ | C70: Becamex UDJ | D70: UPCoM | E70: 5907 | F70: 5914 | G70: 6700 | H70: 7272 | I70: =$E70/F70-1 -> -0.0011836321 | J70: =$E70/G70-1 -> -0.11835821 | K70: =$E70/H70-1 -> -0.18770627 | L70: -131.28 | M70: 0.44 | N70: 7631.25 | O70: 5813
A71: 63 | B71: BT6 | C71: Bê tông 6 | D71: UPCoM | E71: 3400 | F71: 3400 | G71: 3400 | H71: 3400 | I71: =$E71/F71-1 -> 0 | J71: =$E71/G71-1 -> 0 | K71: =$E71/H71-1 -> 0 | L71: -1.22 | M71: -0.1 | N71: 3400 | O71: 3400
A72: 64 | B72: ACE | C72: Bê tông An Giang | D72: UPCoM | E72: 36242 | F72: 35884 | G72: 36524 | H72: 42320.66 | I72: =$E72/F72-1 -> 0.0099765912 | J72: =$E72/G72-1 -> -0.0077209506 | K72: =$E72/H72-1 -> -0.14363339 | L72: 6.44 | M72: 1.5 | N72: 43112.68 | O72: 33175
A73: 65 | B73: BHC | C73: Bê tông Biên Hòa | D73: UPCoM | E73: 900 | F73: 900 | G73: 900 | H73: 1200 | I73: =$E73/F73-1 -> 0 | J73: =$E73/G73-1 -> 0 | K73: =$E73/H73-1 -> -0.25 | L73: -79.95 | M73: -0.05 | N73: 1600 | O73: 866
A74: 66 | B74: HCC | C74: Bê tông Hòa Cầm | D74: HNX | E74: 28000 | F74: 28100 | G74: 25700 | H74: 30500 | I74: =$E74/F74-1 -> -0.0035587189 | J74: =$E74/G74-1 -> 0.089494163 | K74: =$E74/H74-1 -> -0.081967213 | L74: 4.04 | M74: 1.38 | N74: 31500 | O74: 21685.8
A75: 67 | B75: BTD | C75: Bê tông ly tâm Thủ Đức | D75: UPCoM | E75: 18600 | F75: 17000 | G75: 18000 | H75: 16062 | I75: =$E75/F75-1 -> 0.094117647 | J75: =$E75/G75-1 -> 0.033333333 | K75: =$E75/H75-1 -> 0.1580127 | L75: 9.9 | M75: 0.63 | N75: 21900 | O75: 15100
A76: 68 | B76: FCM | C76: Bê tông Phan Vũ Hà Nam | D76: HOSE | E76: 3060 | F76: 3076.65 | G76: 3231.45 | H76: 3304.12 | I76: =$E76/F76-1 -> -0.0054117303 | J76: =$E76/G76-1 -> -0.053056677 | K76: =$E76/H76-1 -> -0.073883515 | L76: 8.05 | M76: 0.26 | N76: 4018.77 | O76: 2970.22
A77: 69 | B77: XMC | C77: Bê tông Xuân Mai | D77: UPCoM | E77: 9800 | F77: 9889 | G77: 10000 | H77: 9934 | I77: =$E77/F77-1 -> -0.0089998989 | J77: =$E77/G77-1 -> -0.02 | K77: =$E77/H77-1 -> -0.013489028 | L77: 16.79 | M77: 0.77 | N77: 10546 | O77: 6418
A78: 70 | B78: TPS | C78: Bến bãi vận tải Sài Gòn | D78: UPCoM | E78: 58000 | F78: 47400 | G78: 47400 | H78: 47550 | I78: =$E78/F78-1 -> 0.22362869 | J78: =$E78/G78-1 -> 0.22362869 | K78: =$E78/H78-1 -> 0.21976866 | L78: 8 | M78: 2.92 | N78: 64002.3 | O78: 34734.32
A79: 71 | B79: HNB | C79: Bến xe Hà Nội | D79: UPCoM | E79: 12300 | F79: 12300 | G79: 12000 | H79: 11761.4 | I79: =$E79/F79-1 -> 0 | J79: =$E79/G79-1 -> 0.025 | K79: =$E79/H79-1 -> 0.045793868 | L79: 9.42 | M79: 1.01 | N79: 17642.1 | O79: 10101.52
A80: 72 | B80: WCS | C80: Bến xe Miền Tây | D80: HNX | E80: 296000 | F80: 300000 | G80: 305000 | H80: 279200 | I80: =$E80/F80-1 -> -0.013333333 | J80: =$E80/G80-1 -> -0.029508197 | K80: =$E80/H80-1 -> 0.06017192 | L80: 10.74 | M80: 2.89 | N80: 355000 | O80: 260000
... A83: 75 | B83: ABI | C83: BH NH Nông Nghiệp | D83: UPCoM | E83: 18810 | F83: 18791 | G83: 19282 | H83: 20390 | I83: =$E83/F83-1 -> 0.0010111223 | J83: =$E83/G83-1 -> -0.024478789 | K83: =$E83/H83-1 -> -0.077488965 | L83: 6.57 | M83: 1.02 | N83: 22160.44 | O83: 18438
A84: 76 | B84: STD | C84: Bia - NGK Sài Gòn - Tây Đô | D84: UPCoM | E84: 6263 | F84: 5700 | G84: 5800 | I84: =$E84/F84-1 -> 0.09877193 | J84: =$E84/G84-1 -> 0.079827586 | K84: =$E84/H84-1 -> #DIV/0! | L84: 24.23 | M84: 0.47
A85: 77 | B85: HAD | C85: Bia Hà Nội - Hải Dương | D85: HNX | E85: 13400 | F85: 13400 | G85: 13400 | H85: 14500 | I85: =$E85/F85-1 -> 0 | J85: =$E85/G85-1 -> 0 | K85: =$E85/H85-1 -> -0.075862069 | L85: 6.18 | M85: 0.69 | N85: 15700 | O85: 13000
A86: 78 | B86: BHP | C86: Bia Hà Nội - Hải Phòng | D86: UPCoM | E86: 7900 | F86: 6900 | G86: 6400 | H86: 7000 | I86: =$E86/F86-1 -> 0.14492754 | J86: =$E86/G86-1 -> 0.234375 | K86: =$E86/H86-1 -> 0.12857143 | L86: 23.36 | M86: 0.47 | N86: 9300 | O86: 5700
A87: 79 | B87: HHB | C87: Bia Hà Nội - Hồng Hà | D87: UPCoM | E87: 28900 | F87: 28900 | G87: 28900 | H87: 24002.5 | I87: =$E87/F87-1 -> 0 | J87: =$E87/G87-1 -> 0 | K87: =$E87/H87-1 -> 0.20404125
A88: 80 | B88: BHK | C88: Bia Hà Nội - Kim Bài | D88: UPCoM | E88: 12000 | F88: 12000 | G88: 13100 | H88: 11041.26 | I88: =$E88/F88-1 -> 0 | J88: =$E88/G88-1 -> -0.083969466 | K88: =$E88/H88-1 -> 0.086832481 | L88: 9.86 | M88: 0.95 | N88: 15064.77 | O88: 9357
A89: 81 | B89: BBM | C89: Bia Hà Nội - Nam Định | D89: UPCoM | E89: 7500 | F89: 7500 | G89: 8600 | H89: 9437.47 | I89: =$E89/F89-1 -> 0 | J89: =$E89/G89-1 -> -0.12790698 | K89: =$E89/H89-1 -> -0.20529549 | L89: 11.48 | M89: 0.6 | N89: 9441.32 | O89: 5828.57
A90: 82 | B90: BQB | C90: Bia Hà Nội - Quảng Bình | D90: UPCoM | E90: 3566 | F90: 3600 | G90: 3900 | H90: 4700 | I90: =$E90/F90-1 -> -0.0094444444 | J90: =$E90/G90-1 -> -0.085641026 | K90: =$E90/H90-1 -> -0.2412766 | L90: 406.29 | M90: 0.78 | N90: 5100 | O90: 3350
A91: 83 | B91: BTB | C91: Bia Hà Nội - Thái Bình | D91: UPCoM | E91: 4700 | F91: 4100 | G91: 4800 | H91: 4795 | I91: =$E91/F91-1 -> 0.14634146 | J91: =$E91/G91-1 -> -0.020833333 | K91: =$E91/H91-1 -> -0.019812304 | L91: 87.61 | M91: 0.32 | N91: 6341 | O91: 3848
A92: 84 | B92: THB | C92: Bia Hà Nội - Thanh Hóa | D92: HNX | E92: 9000 | F92: 9000 | G92: 9700 | H92: 9200 | I92: =$E92/F92-1 -> 0 | J92: =$E92/G92-1 -> -0.072164948 | K92: =$E92/H92-1 -> -0.02173913 | L92: 8.86 | M92: 0.69 | N92: 10700 | O92: 8200
A93: 85 | B93: SBL | C93: Bia Sài Gòn - Bạc Liêu | D93: UPCoM | E93: 6200 | F93: 5900 | G93: 5100 | H93: 6500 | I93: =$E93/F93-1 -> 0.050847458 | J93: =$E93/G93-1 -> 0.21568627 | K93: =$E93/H93-1 -> -0.046153846 | L93: 22.25 | M93: 0.41 | N93: 7837 | O93: 4485
A94: 86 | B94: BSH | C94: Bia Sài Gòn - Hà Nội | D94: UPCoM | E94: 16200 | F94: 16200 | G94: 16200 | H94: 15654.24 | I94: =$E94/F94-1 -> 0 | J94: =$E94/G94-1 -> 0 | K94: =$E94/H94-1 -> 0.034863398 | L94: 6.5 | M94: 0.95 | N94: 20499.6 | O94: 15100
A95: 87 | B95: WSB | C95: Bia Sài Gòn - Miền Tây | D95: UPCoM | E95: 55400 | F95: 55375 | G95: 55900 | H95: 53137.92 | I95: =$E95/F95-1 -> 0.00045146727 | J95: =$E95/G95-1 -> -0.0089445438 | K95: =$E95/H95-1 -> 0.042569976 | L95: 7.54 | M95: 1.01 | N95: 62108.88 | O95: 48343.39
A96: 88 | B96: SMB | C96: Bia Sài Gòn - Miền Trung | D96: HOSE | E96: 39150 | F96: 38500 | G96: 38900 | H96: 38829.84 | I96: =$E96/F96-1 -> 0.016883117 | J96: =$E96/G96-1 -> 0.0064267352 | K96: =$E96/H96-1 -> 0.0082452052 | L96: 6.62 | M96: 1.79 | N96: 39560.64 | O96: 36192.72
A97: 89 | B97: SB1 | C97: Bia Sài Gòn - Nghệ Tĩnh | D97: UPCoM | E97: 7600 | F97: 7640 | G97: 7700 | H97: 6010 | I97: =$E97/F97-1 -> -0.0052356021 | J97: =$E97/G97-1 -> -0.012987013 | K97: =$E97/H97-1 -> 0.26455907 | L97: 4.55 | M97: 0.57 | N97: 7800 | O97: 5827
A98: 90 | B98: BSP | C98: Bia Sài Gòn - Phú Thọ | D98: UPCoM | E98: 12300 | F98: 12300 | G98: 10500 | H98: 9727.37 | I98: =$E98/F98-1 -> 0 | J98: =$E98/G98-1 -> 0.17142857 | K98: =$E98/H98-1 -> 0.26447334 | L98: 7.84 | M98: 0.85 | N98: 15468 | O98: 8409.18
A99: 91 | B99: BSQ | C99: Bia Sài Gòn - Quảng Ngãi | D99: UPCoM | E99: 18000 | F99: 18000 | G99: 17500 | H99: 17667.84 | I99: =$E99/F99-1 -> 0 | J99: =$E99/G99-1 -> 0.028571429 | K99: =$E99/H99-1 -> 0.018800261 | L99: 6.67 | M99: 0.95 | N99: 20318.02 | O99: 13342.9
... A103: 95 | B103: BSD | C103: Bia, rượu Sài Gòn - Đồng Xuân | D103: UPCoM | E103: 16500 | F103: 15100 | G103: 15100 | H103: 21981.1 | I103: =$E103/F103-1 -> 0.092715232 | J103: =$E103/G103-1 -> 0.092715232 | K103: =$E103/H103-1 -> -0.24935513 | L103: 9.23 | M103: 0.71 | N103: 21981.1 | O103: 8027.88
A104: 96 | B104: BID | C104: BIDV | D104: HOSE | E104: 39050 | F104: 38000 | G104: 41171.02 | H104: 38452.65 | I104: =$E104/F104-1 -> 0.027631579 | J104: =$E104/G104-1 -> -0.051517305 | K104: =$E104/H104-1 -> 0.01553469 | L104: 8.59 | M104: 1.47 | N104: 54367.5 | O104: 34700 | P104: 11.98 | Q104: 2.05
A105: 97 | B105: BTH | C105: Biến thế và Vật liệu Điện Hà Nội | D105: UPCoM | E105: 20600 | F105: 21138 | G105: 19814.27 | H105: 23201.87 | I105: =$E105/F105-1 -> -0.025451793 | J105: =$E105/G105-1 -> 0.039654754 | K105: =$E105/H105-1 -> -0.11214053 | L105: 2.1 | M105: 0.92 | N105: 41378.76 | O105: 19357.72
A106: 98 | B106: BMK | C106: Black Cat | D106: UPCoM | E106: 10809 | F106: 12897 | G106: 14000 | H106: 14000 | I106: =$E106/F106-1 -> -0.16189812 | J106: =$E106/G106-1 -> -0.22792857 | K106: =$E106/H106-1 -> -0.22792857 | L106: 61.91 | M106: 1.05 | N106: 18000 | O106: 10809
A107: 99 | B107: DXG | C107: Bluemarq Group | D107: HOSE | E107: 10700 | F107: 10300 | G107: 11900 | H107: 15000.12 | I107: =$E107/F107-1 -> 0.038834951 | J107: =$E107/G107-1 -> -0.10084034 | K107: =$E107/H107-1 -> -0.28667237 | L107: 68.32 | M107: 0.95 | N107: 21228.24 | O107: 9970 | P107: 35.83 | Q107: 1.27
A108: 100 | B108: PVB | C108: Bọc ống Dầu khí Việt Nam | D108: HNX | E108: 21000 | F108: 21000 | G108: 23300 | H108: 35800 | I108: =$E108/F108-1 -> 0 | J108: =$E108/G108-1 -> -0.098712446 | K108: =$E108/H108-1 -> -0.41340782 | L108: 5.25 | M108: 1 | N108: 42000 | O108: 20500
A109: 101 | B109: RAL | C109: Bóng đèn Phích nước Rạng Đông | D109: HOSE | E109: 80200 | F109: 79000 | G109: 83900 | H109: 90405.3 | I109: =$E109/F109-1 -> 0.015189873 | J109: =$E109/G109-1 -> -0.044100119 | K109: =$E109/H109-1 -> -0.11288387 | L109: 4.45 | M109: 0.54 | N109: 92349.5 | O109: 77900
A110: 102 | B110: BOT | C110: BOT Cầu Thái Hà | D110: UPCoM | E110: 1471 | F110: 1493 | G110: 1700 | H110: 1800 | I110: =$E110/F110-1 -> -0.014735432 | J110: =$E110/G110-1 -> -0.13470588 | K110: =$E110/H110-1 -> -0.18277778 | L110: -0.86 | M110: -1.92 | N110: 2500 | O110: 1468
A111: 103 | B111: BBT | C111: Bông Bạch Tuyết | D111: UPCoM | E111: 12500 | F111: 12500 | G111: 11891.6 | H111: 11491.7 | I111: =$E111/F111-1 -> 0 | J111: =$E111/G111-1 -> 0.051162165 | K111: =$E111/H111-1 -> 0.087741587 | L111: 7.71 | M111: 0.93 | N111: 17985.09 | O111: 9628.36
A112: 104 | B112: BVN | C112: Bông Việt Nam | D112: UPCoM | E112: 18100 | F112: 17650 | G112: 18100 | H112: 15100 | I112: =$E112/F112-1 -> 0.025495751 | J112: =$E112/G112-1 -> 0 | K112: =$E112/H112-1 -> 0.1986755 | L112: 3.15 | M112: 0.67 | N112: 25800 | O112: 12500
A113: 105 | B113: LIX | C113: Bột Giặt LIX | D113: HOSE | E113: 24950 | F113: 24950 | G113: 27000 | H113: 32437.51 | I113: =$E113/F113-1 -> 0 | J113: =$E113/G113-1 -> -0.075925926 | K113: =$E113/H113-1 -> -0.23082875 | L113: 8.74 | M113: 1.64 | N113: 38300.85 | O113: 24800
A114: 106 | B114: NET | C114: Bột giặt Net | D114: HNX | E114: 59800 | F114: 59900 | G114: 65600 | H114: 67800 | I114: =$E114/F114-1 -> -0.0016694491 | J114: =$E114/G114-1 -> -0.088414634 | K114: =$E114/H114-1 -> -0.1179941 | L114: 10.84 | M114: 2.28 | N114: 78218.37 | O114: 58500
A115: 107 | B115: BMV | C115: Bột mỳ Vinafood 1 | D115: UPCoM | E115: 2700 | F115: 2700 | G115: 3000 | H115: 5650 | I115: =$E115/F115-1 -> 0 | J115: =$E115/G115-1 -> -0.1 | K115: =$E115/H115-1 -> -0.52212389 | L115: 9.89 | M115: 0.26 | N115: 6900 | O115: 2700
A116: 108 | B116: CTB | C116: Bơm Hải Dương | D116: HNX | E116: 16100 | F116: 16395.58 | G116: 16211.36 | H116: 15658.7 | I116: =$E116/F116-1 -> -0.01802803 | J116: =$E116/G116-1 -> -0.0068692571 | K116: =$E116/H116-1 -> 0.028182416 | L116: 6.06 | M116: 1.07 | N116: 19651.12 | O116: 14277.05
A117: 109 | B117: VTP | C117: Bưu chính Viettel | D117: HOSE | E117: 51500 | F117: 48000 | G117: 53682.3 | H117: 61928.31 | I117: =$E117/F117-1 -> 0.072916667 | J117: =$E117/G117-1 -> -0.040652133 | K117: =$E117/H117-1 -> -0.16839326 | L117: 23.15 | M117: 4.5 | N117: 80795.13 | O117: 44800 | P117: 24.33 | Q117: 5.96
A118: 110 | B118: BVL | C118: BV Land | D118: UPCoM | E118: 14500 | F118: 13700 | G118: 14100 | H118: 14101.1 | I118: =$E118/F118-1 -> 0.058394161 | J118: =$E118/G118-1 -> 0.028368794 | K118: =$E118/H118-1 -> 0.028288573 | L118: 7.8 | M118: 1.18 | N118: 17277.64 | O118: 12233.68
A119: 111 | B119: VCM | C119: BV Life | D119: HNX | E119: 6300 | F119: 6800 | G119: 8800 | H119: 9500 | I119: =$E119/F119-1 -> -0.073529412 | J119: =$E119/G119-1 -> -0.28409091 | K119: =$E119/H119-1 -> -0.33684211 | L119: 1.78 | M119: 0.46 | N119: 11200 | O119: 5800
A120: 112 | B120: SPC | C120: BV Thực vật Sài Gòn | D120: HNX | E120: 10300 | F120: 9500 | G120: 8700 | H120: 7800 | I120: =$E120/F120-1 -> 0.084210526 | J120: =$E120/G120-1 -> 0.18390805 | K120: =$E120/H120-1 -> 0.32051282 | L120: 3.47 | M120: 0.73 | N120: 12100 | O120: 7100
A121: 113 | B121: FGL | C121: Cà Phê Gia Lai | D121: UPCoM | E121: 5000 | F121: 4400 | G121: 4400 | H121: 6800 | I121: =$E121/F121-1 -> 0.13636364 | J121: =$E121/G121-1 -> 0.13636364 | K121: =$E121/H121-1 -> -0.26470588 | L121: -6.19 | M121: 133.96 | N121: 10100 | O121: 3900
A122: 114 | B122: PCF | C122: Cà phê PETEC | D122: UPCoM | E122: 3000 | F122: 3000 | G122: 3333 | H122: 5700 | I122: =$E122/F122-1 -> 0 | J122: =$E122/G122-1 -> -0.099909991 | K122: =$E122/H122-1 -> -0.47368421 | L122: 89.04 | M122: 0.42 | N122: 7627 | O122: 2840
A123: 115 | B123: CPA | C123: Cà phê Phước An | D123: UPCoM | E123: 8800 | F123: 8800 | G123: 8800 | H123: 7700 | I123: =$E123/F123-1 -> 0 | J123: =$E123/G123-1 -> 0 | K123: =$E123/H123-1 -> 0.14285714 | L123: -44.24 | M123: 6.78 | N123: 10000 | O123: 4900
A124: 116 | B124: CFV | C124: Cà phê Thắng Lợi | D124: UPCoM | E124: 17000 | F124: 17000 | G124: 17000 | H124: 19800 | I124: =$E124/F124-1 -> 0 | J124: =$E124/G124-1 -> 0 | K124: =$E124/H124-1 -> -0.14141414 | L124: 14.47 | M124: 1.11 | N124: 29300 | O124: 15100
A125: 117 | B125: TAN | C125: Cà phê Thuận An | D125: OTC | F125: 46700 | G125: 46700 | H125: 43700 | I125: =$E125/F125-1 -> -1 | J125: =$E125/G125-1 -> -1 | K125: =$E125/H125-1 -> -1
A126: 118 | B126: CMM | C126: Camimex | D126: UPCoM | E126: 18400 | F126: 18400 | G126: 17387 | H126: 22262 | I126: =$E126/F126-1 -> 0 | J126: =$E126/G126-1 -> 0.05826192 | K126: =$E126/H126-1 -> -0.17347947 | L126: 28.5 | M126: 1.5 | N126: 25800 | O126: 14023
A127: 119 | B127: CMX | C127: CAMIMEX Group | D127: HOSE | E127: 4750 | F127: 4670 | G127: 5500 | H127: 6270 | I127: =$E127/F127-1 -> 0.017130621 | J127: =$E127/G127-1 -> -0.13636364 | K127: =$E127/H127-1 -> -0.24242424 | L127: 5.82 | M127: 0.37 | N127: 7860 | O127: 4610
A128: 120 | B128: TTS | C128: Cán thép Thái Trung | D128: UPCoM | E128: 5800 | F128: 6500 | G128: 16200 | H128: 4500 | I128: =$E128/F128-1 -> -0.10769231 | J128: =$E128/G128-1 -> -0.64197531 | K128: =$E128/H128-1 -> 0.28888889 | L128: -139.61 | M128: 0.97 | N128: 16200 | O128: 4500
A129: 121 | B129: CAG | C129: Cảng An Giang | D129: HNX | E129: 5600 | F129: 5600 | G129: 6200 | H129: 6500 | I129: =$E129/F129-1 -> 0 | J129: =$E129/G129-1 -> -0.096774194 | K129: =$E129/H129-1 -> -0.13846154 | L129: 23.03 | M129: 0.53 | N129: 7800 | O129: 5600
A130: 122 | B130: CCR | C130: Cảng Cam Ranh | D130: HNX | E130: 14000 | F130: 14000 | G130: 13700 | H130: 12000.24 | I130: =$E130/F130-1 -> 0 | J130: =$E130/G130-1 -> 0.02189781 | K130: =$E130/H130-1 -> 0.16664333 | L130: 8.16 | M130: 1.19 | N130: 14300 | O130: 11143.08
A131: 123 | B131: CLL | C131: Cảng Cát Lái | D131: HOSE | E131: 26900 | F131: 27500 | G131: 27541.5 | H131: 27907.5 | I131: =$E131/F131-1 -> -0.021818182 | J131: =$E131/G131-1 -> -0.023292123 | K131: =$E131/H131-1 -> -0.036101406 | L131: 9.39 | M131: 1.61 | N131: 30710.95 | O131: 26626.5
A132: 124 | B132: CCT | C132: Cảng Cần Thơ | D132: UPCoM | E132: 8900 | F132: 8900 | G132: 8900 | H132: 11500 | I132: =$E132/F132-1 -> 0 | J132: =$E132/G132-1 -> 0 | K132: =$E132/H132-1 -> -0.22608696 | L132: 28.66 | M132: 0.91 | N132: 13100 | O132: 7753
A133: 125 | B133: CMP | C133: Cảng Chân Mây | D133: UPCoM | E133: 8000 | F133: 8000 | G133: 8000 | H133: 8000 | I133: =$E133/F133-1 -> 0 | J133: =$E133/G133-1 -> 0 | K133: =$E133/H133-1 -> 0 | L133: 9.15 | M133: 0.67 | N133: 8000 | O133: 7950.96
A134: 126 | B134: CCP | C134: Cảng Cửa Cấm | D134: UPCoM | E134: 23500 | F134: 20500 | G134: 20500 | H134: 15065.3 | I134: =$E134/F134-1 -> 0.14634146 | J134: =$E134/G134-1 -> 0.14634146 | K134: =$E134/H134-1 -> 0.55987601 | L134: 13.37 | M134: 1.09 | N134: 24314.25 | O134: 14380.69
...
